setup.py
transfer_lib/__init__.py
transfer_lib/ftp.py
transfer_lib/http.py
transfer_lib.egg-info/PKG-INFO
transfer_lib.egg-info/SOURCES.txt
transfer_lib.egg-info/dependency_links.txt
transfer_lib.egg-info/requires.txt
transfer_lib.egg-info/top_level.txt