Metadata-Version: 1.0
Name: transfer-lib
Version: 1.0.1
Summary: Transfer Library
Home-page: https://github.com/Akira-Taniguchi/transfer_libb
Author: AkiraTaniguchi
Author-email: dededededaiou2003@yahoo.co.jp
License: MIT
Keywords: ftp sftp ftps https http transfer download upload
Platform: UNKNOWN
Classifier: Development Status :: 5 - Production/Stable
Classifier: Programming Language :: Python :: 2.7
Classifier: Intended Audience :: Developers
Classifier: License :: OSI Approved :: MIT License
